doccli/__init__.py
doccli/config.py
doccli/parse.py
doc_cli-0.0.4.dist-info/LICENSE
doc_cli-0.0.4.dist-info/WHEEL
doc_cli-0.0.4.dist-info/METADATA
doc_cli-0.0.4.dist-info/RECORD
