Metadata-Version: 2.1
Name: doc-cli
Version: 0.0.4
Summary: Build Config classes that can be quickly turned into CLI specifications
Home-page: https://github.com/mayansalama/doccli/
License: Apache-2.0
Author: mayansalama
Author-email: micsalama@gmail.com
Requires-Python: >=3.6,<4.0
Classifier: License :: OSI Approved :: Apache Software License
Classifier: Programming Language :: Python :: 3
Classifier: Programming Language :: Python :: 3.6
Classifier: Programming Language :: Python :: 3.7
Requires-Dist: decli (>=0.5.1,<0.6.0)
Requires-Dist: docstring-parser (>=0.3,<0.4)
Requires-Dist: pyyaml (>=5.1.2,<6.0.0)
Project-URL: Repository, https://github.com/mayansalama/doccli
